lerobot_teleoperator_teleop/__init__.py
lerobot_teleoperator_teleop/config_teleop.py
lerobot_teleoperator_teleop/teleop.py
lerobot_teleoperator_teleop-0.0.2.dist-info/licenses/LICENSE
lerobot_teleoperator_teleop-0.0.2.dist-info/METADATA
lerobot_teleoperator_teleop-0.0.2.dist-info/WHEEL
lerobot_teleoperator_teleop-0.0.2.dist-info/top_level.txt
lerobot_teleoperator_teleop-0.0.2.dist-info/RECORD
