Metadata-Version: 2.4
Name: lerobot_teleoperator_teleop
Version: 0.0.2
Summary: LeRobot teleop integration
Author-email: Spes Robotics <contact@spes.ai>
License:                                  Apache License
Classifier: Programming Language :: Python :: 3
Classifier: License :: OSI Approved :: Apache Software License
Classifier: Operating System :: OS Independent
Requires-Python: >=3.10
License-File: LICENSE
Requires-Dist: numpy
Requires-Dist: transforms3d
Requires-Dist: teleop
Requires-Dist: lerobot>=0.4
Dynamic: license-file
